Arquitectura/Laboratorio 2/kb_controller.sv
module PS2(
    input logic ps2_clk, // PS2 Clock
    input logic ps2_data, //PS2 Data
    output logic [7:0] leds // 8 LEDs
);

    logic [3:0] count = 11;
    logic paridad;
    logic [7:0] aux;
    always_ff @(negedge ps2_clk) begin
        if(count == 11) begin 
            if(~ps2_data) begin 
                count <= 1;
                paridad <= 1;
            end
            leds <= 8'b00000000;
        end
        else if(count < 9) begin 
            aux[count-1] <= ps2_data;
            if(ps2_data) begin 
                paridad <= ~paridad;
            end

            count <= count + 1;
        end
        else if(count == 9) begin 
            if(paridad == ps2_data) begin 
                leds <= aux;
            end
            else begin 
                leds <= 8'b00000000;
            end

            count <= 10;
        end
        else begin 
            count <= 11;
        end
    end

endmodule

Arquitectura/Laboratorio 2/kb_controller_tb.sv
`timescale 1ns/100ps

module kb_controller_tb;

    logic ps2_clk_tb = 1;
    logic ps2_data_tb = 1;
    logic [7:0] leds_tb;

    PS2 ps2 (.ps2_clk(ps2_clk_tb), .ps2_data(ps2_data_tb), .leds(leds_tb));

    always #50 ps2_clk_tb = ~ps2_clk_tb;
    initial begin
        $dumpfile("kb_controller_tb.vcd");
        $dumpvars(0, kb_controller_tb);

        #125
            ps2_data_tb = 1;
        #100
            ps2_data_tb = 0; // Inicio
        #100
            ps2_data_tb = 1; // Bit 0
        #100
            ps2_data_tb = 0; // Bit 1
        #100
            ps2_data_tb = 0; // Bit 2
        #100
            ps2_data_tb = 1; // Bit 3
        #100
            ps2_data_tb = 0; // Bit 4
        #100
            ps2_data_tb = 0; // Bit 5
        #100
            ps2_data_tb = 1; // Bit 6
        #100
            ps2_data_tb = 0; // Bit 7
        #100
            ps2_data_tb = 0; // Paridad
        #100
            ps2_data_tb = 1; // Stop
        #100
            ps2_data_tb = 1;
        #100
            ps2_data_tb = 1;
        #100
            ps2_data_tb = 1;
        #100 $finish;
    end
endmodule

Arquitectura/Laboratorio 2/kb_controller_tb.vcd
$date
	Thu Feb 20 20:57:26 2025
$end
$version
	Icarus Verilog
$end
$timescale
	100ps
$end
$scope module kb_controller_tb $end
$var wire 8 ! leds_tb [7:0] $end
$var reg 1 " ps2_clk_tb $end
$var reg 1 # ps2_data_tb $end
$scope module ps2 $end
$var wire 1 " ps2_clk $end
$var wire 1 # ps2_data $end
$var reg 8 $ aux [7:0] $end
$var reg 4 % count [3:0] $end
$var reg 8 & leds [7:0] $end
$var reg 1 ' paridad $end
$upscope $end
$upscope $end
$enddefinitions $end
#0
$dumpvars
x'
bx &
b1011 %
bx $
1#
1"
bx !
$end
#500
b0 !
b0 &
0"
#1000
1"
#1500
0"
#2000
1"
#2250
0#
#2500
1'
b1 %
0"
#3000
1"
#3250
1#
#3500
b10 %
0'
bx1 $
0"
#4000
1"
#4250
0#
#4500
b11 %
bx01 $
0"
#5000
1"
#5500
b100 %
bx001 $
0"
#6000
1"
#6250
1#
#6500
b101 %
1'
bx1001 $
0"
#7000
1"
#7250
0#
#7500
b110 %
bx01001 $
0"
#8000
1"
#8500
b111 %
bx001001 $
0"
#9000
1"
#9250
1#
#9500
b1000 %
0'
bx1001001 $
0"
#10000
1"
#10250
0#
#10500
b1001 %
b1001001 $
0"
#11000
1"
#11250
1#
#11500
b1010 %
0"
#12000
1"
#12500
b1011 %
0"
